ring.py
ring_me_up-0.0.1.dist-info/METADATA
ring_me_up-0.0.1.dist-info/WHEEL
ring_me_up-0.0.1.dist-info/entry_points.txt
ring_me_up-0.0.1.dist-info/top_level.txt
ring_me_up-0.0.1.dist-info/RECORD
