Metadata-Version: 2.1
Name: ring-me-up
Version: 0.0.1
Summary: Send an alarm to your iPhone to ring you up from a failed script when you are asleep.
Author: WestXu
Project-URL: repository, https://github.com/WestXu/RingMeUp
Requires-Dist: pyicloud
